{
    "tests/test_unpack.py::test_unpack_single_known_message_1": {
        "Description": "",
        "Fields": {
            "age_gps_data": {
                "Description": "Age of Differential GPS Data (secs)",
                "Value": ""
            },
            "altitude": {
                "Description": "Antenna Alt above sea level (mean)",
                "Value": 4.03
            },
            "altitude_units": {
                "Description": "Units of altitude (meters)",
                "Value": "M"
            },
            "geo_sep": {
                "Description": "Geoidal Separation",
                "Value": 35.78
            },
            "geo_sep_units": {
                "Description": "Units of Geoidal Separation (meters)",
                "Value": "M"
            },
            "gps_qual": {
                "Description": "GPS Quality Indicator",
                "Value": 4
            },
            "horizontal_dil": {
                "Description": "Horizontal Dilution of Precision",
                "Value": 0.5
            },
            "lat": {
                "Description": "Latitude",
                "Value": 5741.1549
            },
            "lat_dir": {
                "Description": "Latitude Direction",
                "Value": "N"
            },
            "lon": {
                "Description": "Longitude",
                "Value": 1153.1748
            },
            "lon_dir": {
                "Description": "Longitude Direction",
                "Value": "E"
            },
            "num_sats": {
                "Description": "Number of Satellites in use",
                "Value": 37
            },
            "ref_station_id": {
                "Description": "Differential Reference Station ID",
                "Value": ""
            },
            "timestamp": {
                "Description": "Timestamp",
                "Value": 122203.19
            }
        },
        "Talker": "GNGGA"
    }
}